descartcan/__init__.py
descartcan/config/__init__.py
descartcan/config/config.py
descartcan/llm/__init__.py
descartcan/llm/exceptions.py
descartcan/llm/factory.py
descartcan/llm/llm.py
descartcan/llm/llm_enhanced.py
descartcan/llm/mcp_client.py
descartcan/llm/parameters.py
descartcan/llm/strategy.py
descartcan/llm/models/__init__.py
descartcan/llm/models/alibaba.py
descartcan/llm/models/anthropic.py
descartcan/llm/models/base.py
descartcan/llm/models/bedrock.py
descartcan/llm/models/deepseek.py
descartcan/llm/models/moonshot.py
descartcan/llm/models/ollama.py
descartcan/llm/models/openai.py
descartcan/llm/models/siliconflow.py
descartcan/llm/models/zhipu.py
descartcan/service/__init__.py
descartcan/service/app.py
descartcan/service/launch.py
descartcan/service/api/__init__.py
descartcan/service/api/health_router.py
descartcan/service/api/monitor_api.py
descartcan/service/core/__init__.py
descartcan/service/core/auth.py
descartcan/service/core/events.py
descartcan/service/core/response.py
descartcan/service/database/__init__.py
descartcan/service/database/milvus.py
descartcan/service/database/mysql.py
descartcan/service/exception/__init__.py
descartcan/service/exception/error.py
descartcan/service/exception/exception.py
descartcan/service/exception/handler.py
descartcan/service/generated/__init__.py
descartcan/service/generated/vector_generation_pb2.py
descartcan/service/generated/vector_generation_pb2_grpc.py
descartcan/service/generated/vector_retrival_pb2.py
descartcan/service/generated/vector_retrival_pb2_grpc.py
descartcan/service/grpc/__init__.py
descartcan/service/grpc/vector_generation_client.py
descartcan/service/grpc/vector_retrival_client.py
descartcan/service/middleware/__init__.py
descartcan/service/middleware/base.py
descartcan/service/middleware/logging.py
descartcan/service/middleware/rate_limit.py
descartcan/service/middleware/request_id.py
descartcan/service/middleware/white_list.py
descartcan/service/models/__init__.py
descartcan-2025.11.13.5.dist-info/METADATA
descartcan-2025.11.13.5.dist-info/WHEEL
descartcan-2025.11.13.5.dist-info/top_level.txt
descartcan-2025.11.13.5.dist-info/RECORD
